{
  "project_info": {
    "project_number": "436921850790",
    "firebase_url": "https://androidappskeleton-67a17.firebaseio.com",
    "project_id": "androidappskeleton-67a17",
    "storage_bucket": "androidappskeleton-67a17.appspot.com"
  },
  "client": [
    {
      "client_info": {
        "mobilesdk_app_id": "1:436921850790:android:eecf6b11f7fa5832",
        "android_client_info": {
          "package_name": "com.jahanbabu.AndroidAppSkeleton"
        }
      },
      "oauth_client": [
        {
          "client_id": "436921850790-oqpucj3tdpd8efgq0oubh17evpfgqu8r.apps.googleusercontent.com",
          "client_type": 1,
          "android_info": {
            "package_name": "com.jahanbabu.AndroidAppSkeleton",
            "certificate_hash": "7a135f36834e901187f706a7489a965d18a3c469"
          }
        },
        {
          "client_id": "436921850790-kphbo6snjplap1jloc7ss06eehdva1lv.apps.googleusercontent.com",
          "client_type": 3
        }
      ],
      "api_key": [
        {
          "current_key": "AIzaSyAH5XtwJVBQ551ntoqoOCAVfAz2AXoIZR8"
        }
      ],
      "services": {
        "analytics_service": {
          "status": 1
        },
        "appinvite_service": {
          "status": 2,
          "other_platform_oauth_client": [
            {
              "client_id": "436921850790-kphbo6snjplap1jloc7ss06eehdva1lv.apps.googleusercontent.com",
              "client_type": 3
            }
          ]
        },
        "ads_service": {
          "status": 2
        }
      }
    }
  ],
  "configuration_version": "1"
}